velruse_naver/__init__.py
velruse_naver/locale/en/LC_MESSAGES/velruse-naver.mo
velruse_naver/locale/ko/LC_MESSAGES/velruse-naver.mo
velruse_naver-0.1.1.dist-info/COPYING
velruse_naver-0.1.1.dist-info/METADATA
velruse_naver-0.1.1.dist-info/WHEEL
velruse_naver-0.1.1.dist-info/entry_points.txt
velruse_naver-0.1.1.dist-info/top_level.txt
velruse_naver-0.1.1.dist-info/RECORD
