Metadata-Version: 2.1
Name: velruse-naver
Version: 0.1.1
Summary: velruse provider for NAVER OAuth2
Home-page: https://github.com/mete0r/velruse-naver
Author: mete0r
Author-email: mete0r@sarangbang.or.kr
License: GNU Affero General Public License v3 or later (AGPLv3+)
Keywords: naver,oauth2,velruse
Platform: UNKNOWN
Classifier: Development Status :: 1 - Planning
Classifier: Intended Audience :: Developers
Classifier: License :: OSI Approved :: GNU Affero General Public License v3 or later (AGPLv3+)
Classifier: Operating System :: OS Independent
Classifier: Programming Language :: Python
Classifier: Programming Language :: Python :: 2.7
Classifier: Programming Language :: Python :: 3.4
Classifier: Programming Language :: Python :: Implementation :: CPython
Requires-Dist: pyramid
Requires-Dist: requests
Requires-Dist: velruse
Provides-Extra: test
Requires-Dist: babel (>=2.6.0); extra == 'test'
Requires-Dist: coverage (>=4.5.1); extra == 'test'
Requires-Dist: pytest (>=3.9.2); extra == 'test'
Requires-Dist: zope.testrunner (>=4.8.1); extra == 'test'
